README
setup.py
example_project/__init__.py
example_project/manage.py
example_project/settings.py
example_project/urls.py
fccdata/__init__.py
fccdata/admin.py
fccdata/load.py
fccdata/models.py
fccdata/parser.py
fccdata/tests.py
fccdata.egg-info/PKG-INFO
fccdata.egg-info/SOURCES.txt
fccdata.egg-info/dependency_links.txt
fccdata.egg-info/top_level.txt
fccdata/management/__init__.py
fccdata/management/commands/__init__.py
fccdata/management/commands/import_hams.py
fccdata/migrations/0001_initial.py
fccdata/migrations/__init__.py