Metadata-Version: 1.0
Name: fccdata
Version: 1.0.0
Summary: Models and load scripts used to import FCC data (priarmily focused on amateur radio) into Django.
Home-page: https://github.com/adamfast/fccdata
Author: Adam Fast
Author-email: adamfast@gmail.com
License: UNKNOWN
Platform: UNKNOWN
Classifier: Development Status :: 5 - Production/Stable
Classifier: Environment :: Web Environment
Classifier: Framework :: Django
Classifier: Intended Audience :: Developers
Classifier: License :: OSI Approved :: BSD License
Classifier: Operating System :: OS Independent
Classifier: Programming Language :: Python
Classifier: Topic :: Utilities
